{"v":"5.6.5","fr":60,"ip":0,"op":60,"w":52,"h":75,"nm":"dudintv-linkedin","ddd":0,"assets":[],"layers":[{"ddd":0,"ind":1,"ty":4,"nm":"N","sr":1,"ks":{"o":{"a":0,"k":100,"ix":11},"r":{"a":0,"k":0,"ix":10},"p":{"a":0,"k":[30.575,50.044,0],"ix":2},"a":{"a":0,"k":[0,0,0],"ix":1},"s":{"a":1,"k":[{"i":{"x":[0.667,0.667,0.667],"y":[1,1,1]},"o":{"x":[0.333,0.333,0.333],"y":[0,0,0]},"t":0,"s":[100,100,100]},{"i":{"x":[0.667,0.667,0.667],"y":[1,1,1]},"o":{"x":[0.333,0.333,0.333],"y":[0,0,0]},"t":10,"s":[115.696,84.029,100]},{"i":{"x":[0.667,0.667,0.667],"y":[1,1,1]},"o":{"x":[0.333,0.333,0.333],"y":[0,0,0]},"t":20,"s":[100,100,100]},{"i":{"x":[0.667,0.667,0.667],"y":[1,1,1]},"o":{"x":[0.333,0.333,0.333],"y":[0,0,0]},"t":30,"s":[92,107,100]},{"i":{"x":[0.667,0.667,0.667],"y":[1,1,1]},"o":{"x":[0.333,0.333,0.333],"y":[0,0,0]},"t":40,"s":[100,100,100]},{"i":{"x":[0.667,0.667,0.667],"y":[1,1,1]},"o":{"x":[0.333,0.333,0.333],"y":[0,0,0]},"t":50,"s":[105,105,100]},{"t":59,"s":[100,100,100]}],"ix":6}},"ao":0,"shapes":[{"ind":0,"ty":"sh","ix":1,"ks":{"a":0,"k":{"i":[[0,0.378],[-1.275,0],[-0.145,-1.473],[0,-2.345],[-0.772,0],[-0.029,0.868],[0.113,1.94],[0.463,0.957],[1.559,0],[1.148,-1.065],[0.947,0],[0.091,-0.68],[0,-1.864],[-0.172,-1.656],[-0.936,0],[-0.071,0.759],[-0.017,0.828],[0,1.629]],"o":[[1.022,-0.711],[1.793,0],[0.343,2.329],[0.034,0.792],[1.192,0],[0.065,-1.942],[-0.102,-1.315],[-0.658,-1.382],[-1.602,0],[-0.073,-0.83],[-0.895,0],[-0.276,1.851],[0.043,1.663],[0.075,0.769],[0.951,0],[0.05,-0.558],[0.033,-1.628],[0,-0.738]],"v":[[-2.965,-3.158],[0.382,-4.453],[2.797,-1.241],[3.049,5.83],[4.257,7.017],[5.54,4.534],[5.465,-1.295],[4.685,-4.75],[1.237,-7.044],[-2.965,-5.155],[-4.299,-6.774],[-5.381,-5.047],[-5.557,0.567],[-5.356,5.56],[-4.223,7.044],[-3.141,5.479],[-3.041,3.401],[-2.965,-1.484]],"c":true},"ix":2},"nm":"Path 1","mn":"ADBE Vector Shape - Group","hd":false},{"ty":"fl","c":{"a":0,"k":[1,1,1,1],"ix":4},"o":{"a":0,"k":100,"ix":5},"r":1,"bm":0,"nm":"Fill 1","mn":"ADBE Vector Graphic - Fill","hd":false}],"ip":0,"op":3600,"st":0,"bm":0},{"ddd":0,"ind":2,"ty":4,"nm":"I","sr":1,"ks":{"o":{"a":0,"k":100,"ix":11},"r":{"a":0,"k":0,"ix":10},"p":{"a":0,"k":[20.548,47.5,0],"ix":2},"a":{"a":0,"k":[0,0,0],"ix":1},"s":{"a":1,"k":[{"i":{"x":[0.667,0.667,0.667],"y":[1,1,1]},"o":{"x":[0.333,0.333,0.333],"y":[0,0,0]},"t":0,"s":[100,100,100]},{"i":{"x":[0.667,0.667,0.667],"y":[1,1,1]},"o":{"x":[0.333,0.333,0.333],"y":[0,0,0]},"t":10,"s":[60,110,100]},{"i":{"x":[0.667,0.667,0.667],"y":[1,1,1]},"o":{"x":[0.333,0.333,0.333],"y":[0,0,0]},"t":20,"s":[100,100,100]},{"i":{"x":[0.667,0.667,0.667],"y":[1,1,1]},"o":{"x":[0.333,0.333,0.333],"y":[0,0,0]},"t":30,"s":[123,85,100]},{"i":{"x":[0.667,0.667,0.667],"y":[1,1,1]},"o":{"x":[0.333,0.333,0.333],"y":[0,0,0]},"t":40,"s":[100,100,100]},{"i":{"x":[0.667,0.667,0.667],"y":[1,1,1]},"o":{"x":[0.333,0.333,0.333],"y":[0,0,0]},"t":50,"s":[105,105,100]},{"t":59,"s":[100,100,100]}],"ix":6}},"ao":0,"shapes":[{"ind":0,"ty":"sh","ix":1,"ks":{"a":0,"k":{"i":[[0,-2.58],[-0.086,-1.701],[-0.958,0],[-0.03,0.784],[0,1.702],[0.101,1.889],[0.933,0],[0.087,-0.613]],"o":[[0,1.703],[0.034,0.746],[1.007,0],[0.061,-1.7],[0,-1.763],[-0.034,-0.737],[-0.824,0],[-0.133,1.14]],"v":[[-1.271,2.618],[-1.145,7.719],[-0.038,9.5],[1.095,7.692],[1.246,2.591],[1.095,-2.888],[-0.038,-4.615],[-1.12,-2.888]],"c":true},"ix":2},"nm":"Path 1","mn":"ADBE Vector Shape - Group","hd":false},{"ind":1,"ty":"sh","ix":2,"ks":{"a":0,"k":{"i":[[0.336,0.324],[0.386,0],[0.319,-0.324],[0,-0.432],[-0.302,-0.324],[-0.352,0],[-0.336,0.306],[0,0.432]],"o":[[-0.319,-0.324],[-0.403,0],[-0.302,0.306],[0,0.468],[0.319,0.306],[0.419,0],[0.336,-0.324],[0,-0.45]],"v":[[1.044,-9.014],[-0.013,-9.5],[-1.095,-9.014],[-1.548,-7.908],[-1.095,-6.72],[-0.088,-6.261],[1.044,-6.72],[1.548,-7.854]],"c":true},"ix":2},"nm":"Path 2","mn":"ADBE Vector Shape - Group","hd":false},{"ty":"mm","mm":5,"nm":"Merge Paths 1","mn":"ADBE Vector Filter - Merge","hd":false},{"ty":"fl","c":{"a":0,"k":[1,1,1,1],"ix":4},"o":{"a":0,"k":100,"ix":5},"r":1,"bm":0,"nm":"Fill 1","mn":"ADBE Vector Graphic - Fill","hd":false}],"ip":0,"op":3600,"st":0,"bm":0},{"ddd":0,"ind":3,"ty":4,"nm":"Ellipse 4","sr":1,"ks":{"o":{"a":0,"k":100,"ix":11},"r":{"a":0,"k":0,"ix":10},"p":{"a":0,"k":[25.93,42.813,0],"ix":2},"a":{"a":0,"k":[0,0,0],"ix":1},"s":{"a":0,"k":[100,100,100],"ix":6}},"ao":0,"shapes":[{"ty":"gr","it":[{"ind":0,"ty":"sh","ix":1,"ks":{"a":1,"k":[{"i":{"x":0.667,"y":1},"o":{"x":0.333,"y":0},"t":0,"s":[{"i":[[-13.294,0],[0,13.275],[12.328,3.391],[0,-21.388]],"o":[[13.294,0],[0,-22.87],[2,13.5],[0,13.275]],"v":[[0,30.313],[24.07,6.277],[-10.43,-30.313],[-24.07,6.277]],"c":true}]},{"i":{"x":0.667,"y":1},"o":{"x":0.333,"y":0},"t":10,"s":[{"i":[[-13.294,0],[0,13.275],[15.917,7.583],[0,-21.388]],"o":[[13.294,0],[0,-22.87],[-1.708,13.333],[0,13.275]],"v":[[0,30.313],[24.695,6.277],[-3.971,-31.021],[-24.07,6.277]],"c":true}]},{"i":{"x":0.667,"y":1},"o":{"x":0.333,"y":0},"t":20,"s":[{"i":[[-13.294,0],[0,13.275],[6.208,11.167],[0,-21.388]],"o":[[13.294,0],[0,-22.87],[-5.542,10.917],[0,13.275]],"v":[[0,31.438],[24.383,6.277],[2.612,-33.354],[-24.07,6.277]],"c":true}]},{"i":{"x":0.667,"y":1},"o":{"x":0.333,"y":0},"t":30,"s":[{"i":[[-13.294,0],[0,13.275],[-0.125,12.125],[0,-21.388]],"o":[[13.294,0],[0,-22.87],[-12.125,4.125],[0,13.275]],"v":[[0,30.313],[24.07,6.277],[6.32,-30.188],[-24.07,6.277]],"c":true}]},{"i":{"x":0.667,"y":1},"o":{"x":0.333,"y":0},"t":40,"s":[{"i":[[-13.294,0],[0,13.275],[5.651,13.543],[0,-21.388]],"o":[[13.294,0],[0,-22.87],[-14.849,8.793],[0,13.275]],"v":[[0,30.313],[24.07,6.277],[-0.581,-31.731],[-24.695,6.277]],"c":true}]},{"i":{"x":0.667,"y":1},"o":{"x":0.333,"y":0},"t":50,"s":[{"i":[[-13.294,0],[0,13.275],[7.96,10.58],[0,-21.388]],"o":[[13.294,0],[0,-22.87],[-4.665,12.58],[0,13.275]],"v":[[-0.125,31.563],[24.07,6.277],[-6.264,-33.142],[-24.366,6.277]],"c":true}]},{"t":59,"s":[{"i":[[-13.294,0],[0,13.275],[12.328,3.391],[0,-21.388]],"o":[[13.294,0],[0,-22.87],[2,13.5],[0,13.275]],"v":[[0,30.313],[24.07,6.277],[-10.43,-30.313],[-24.07,6.277]],"c":true}]}],"ix":2},"nm":"Path 1","mn":"ADBE Vector Shape - Group","hd":false},{"ty":"fl","c":{"a":0,"k":[0.003921568859,0.450980395079,0.698039233685,1],"ix":4},"o":{"a":0,"k":100,"ix":5},"r":1,"bm":0,"nm":"Fill 1","mn":"ADBE Vector Graphic - Fill","hd":false},{"ty":"tr","p":{"a":0,"k":[0,0],"ix":2},"a":{"a":0,"k":[0,0],"ix":1},"s":{"a":0,"k":[100,100],"ix":3},"r":{"a":0,"k":0,"ix":6},"o":{"a":0,"k":100,"ix":7},"sk":{"a":0,"k":0,"ix":4},"sa":{"a":0,"k":0,"ix":5},"nm":"Transform"}],"nm":"Ellipse 4","np":2,"cix":2,"bm":0,"ix":1,"mn":"ADBE Vector Group","hd":false}],"ip":0,"op":3600,"st":0,"bm":0},{"ddd":0,"ind":4,"ty":4,"nm":"Ellipse 7","sr":1,"ks":{"o":{"a":0,"k":100,"ix":11},"r":{"a":0,"k":0,"ix":10},"p":{"a":0,"k":[26.07,39.508,0],"ix":2},"a":{"a":0,"k":[0,0,0],"ix":1},"s":{"a":0,"k":[100,100,100],"ix":6}},"ao":0,"shapes":[{"ty":"gr","it":[{"ind":0,"ty":"sh","ix":1,"ks":{"a":1,"k":[{"i":{"x":0.667,"y":1},"o":{"x":0.333,"y":0},"t":0,"s":[{"i":[[-13.294,0],[0,13.275],[17.5,5],[0,-21.388]],"o":[[13.294,0],[0,-22.87],[8,14.5],[0,13.275]],"v":[[0,33.508],[24.07,9.472],[-18.57,-33.508],[-24.07,9.472]],"c":true}]},{"i":{"x":0.833,"y":0.833},"o":{"x":0.333,"y":0},"t":10,"s":[{"i":[[-13.294,0],[0,13.275],[13.542,6.5],[0,-21.388]],"o":[[13.294,0],[0,-22.87],[4.292,13.125],[0,13.275]],"v":[[0,33.508],[24.07,9.472],[-9.987,-34.133],[-24.07,9.472]],"c":true}]},{"i":{"x":0.667,"y":1},"o":{"x":0.167,"y":0.167},"t":20,"s":[{"i":[[-13.294,0],[0,13.275],[4.708,14.5],[0,-21.388]],"o":[[13.294,0],[0,-22.87],[-1.917,15.375],[0,13.275]],"v":[[0,33.508],[24.07,9.472],[-4.654,-38.258],[-24.07,9.472]],"c":true}]},{"i":{"x":0.667,"y":1},"o":{"x":0.333,"y":0},"t":30,"s":[{"i":[[-13.294,0],[0,13.275],[-2.125,15.125],[0,-21.388]],"o":[[13.294,0],[0,-22.87],[-13.125,11.125],[0,13.275]],"v":[[0,33.508],[24.07,9.472],[0.43,-36.133],[-24.07,9.472]],"c":true}]},{"i":{"x":0.833,"y":0.833},"o":{"x":0.333,"y":0},"t":40,"s":[{"i":[[-13.294,0],[0,13.275],[-0.573,13.72],[0,-21.388]],"o":[[13.294,0],[0,-22.87],[-11.698,10.72],[0,13.275]],"v":[[0,33.508],[24.07,9.472],[-7.247,-35.103],[-24.07,9.472]],"c":true}]},{"i":{"x":0.667,"y":1},"o":{"x":0.167,"y":0.167},"t":50,"s":[{"i":[[-13.294,0],[0,13.275],[9.285,15.735],[0,-21.388]],"o":[[13.294,0],[0,-22.871],[1.285,17.11],[0,13.275]],"v":[[0,33.508],[24.07,9.472],[-14.605,-37.867],[-24.07,9.472]],"c":true}]},{"t":59,"s":[{"i":[[-13.294,0],[0,13.275],[17.5,5],[0,-21.388]],"o":[[13.294,0],[0,-22.87],[8,14.5],[0,13.275]],"v":[[0,33.508],[24.07,9.472],[-18.57,-33.508],[-24.07,9.472]],"c":true}]}],"ix":2},"nm":"Path 1","mn":"ADBE Vector Shape - Group","hd":false},{"ty":"fl","c":{"a":0,"k":[0.023958325386,0.31714335084,0.479166656733,1],"ix":4},"o":{"a":0,"k":100,"ix":5},"r":1,"bm":0,"nm":"Fill 1","mn":"ADBE Vector Graphic - Fill","hd":false},{"ty":"tr","p":{"a":0,"k":[0,0],"ix":2},"a":{"a":0,"k":[0,0],"ix":1},"s":{"a":0,"k":[100,100],"ix":3},"r":{"a":0,"k":0,"ix":6},"o":{"a":0,"k":100,"ix":7},"sk":{"a":0,"k":0,"ix":4},"sa":{"a":0,"k":0,"ix":5},"nm":"Transform"}],"nm":"Ellipse 7","np":2,"cix":2,"bm":0,"ix":1,"mn":"ADBE Vector Group","hd":false}],"ip":0,"op":3600,"st":0,"bm":0},{"ddd":0,"ind":5,"ty":4,"nm":"WhiteBack","sr":1,"ks":{"o":{"a":0,"k":100,"ix":11},"r":{"a":0,"k":0,"ix":10},"p":{"a":1,"k":[{"i":{"x":0.667,"y":1},"o":{"x":0.333,"y":0},"t":0,"s":[26,51,0],"to":[0,0,0],"ti":[0,0,0]},{"i":{"x":0.667,"y":1},"o":{"x":0.333,"y":0},"t":30,"s":[24.25,50.75,0],"to":[0,0,0],"ti":[0,0,0]},{"t":59,"s":[26,51,0]}],"ix":2},"a":{"a":0,"k":[0,0,0],"ix":1},"s":{"a":0,"k":[100,100,100],"ix":6}},"ao":0,"shapes":[{"ty":"gr","it":[{"ind":0,"ty":"sh","ix":1,"ks":{"a":0,"k":{"i":[[-13.255,0],[0,13.255],[13.255,0],[0,-13.255]],"o":[[13.255,0],[0,-13.255],[-13.255,0],[0,13.255]],"v":[[0,24],[24,0],[0,-24],[-24,0]],"c":true},"ix":2},"nm":"Path 1","mn":"ADBE Vector Shape - Group","hd":false},{"ty":"fl","c":{"a":0,"k":[0.61960786581,0.729411780834,0.905882358551,1],"ix":4},"o":{"a":0,"k":100,"ix":5},"r":1,"bm":0,"nm":"Fill 1","mn":"ADBE Vector Graphic - Fill","hd":false},{"ty":"tr","p":{"a":0,"k":[0,0],"ix":2},"a":{"a":0,"k":[0,0],"ix":1},"s":{"a":0,"k":[100,100],"ix":3},"r":{"a":0,"k":0,"ix":6},"o":{"a":0,"k":100,"ix":7},"sk":{"a":0,"k":0,"ix":4},"sa":{"a":0,"k":0,"ix":5},"nm":"Transform"}],"nm":"Ellipse 10","np":2,"cix":2,"bm":0,"ix":1,"mn":"ADBE Vector Group","hd":false}],"ip":0,"op":3600,"st":0,"bm":0}],"markers":[]}